duke_browser_reload.py
django_duke_browser_reload-0.1.0.dist-info/METADATA
django_duke_browser_reload-0.1.0.dist-info/WHEEL
django_duke_browser_reload-0.1.0.dist-info/entry_points.txt
django_duke_browser_reload-0.1.0.dist-info/RECORD
